Workbook

Sheet README
A1: 单身期家庭资产诊断 MVP
A2: 使用两张家庭财务报表进行六维评分、风险识别、连锁诊断和改善建议。
A4: 使用顺序 | B4: 1. 在“示例输入”中替换家庭数据；2. 查看“评分计算”和“六维总览”；3. 查看“连锁诊断”和“建议库”；4. 用样本家庭回测阈值。
A5: 评分原则 | B5: 底层计算保持严格，展示层可以友好表达；红灯硬性风险不得被综合分稀释。
A6: MVP 边界 | B6: 本工具只输出方向性资产结构建议，不输出具体金融产品、保险产品或投资标的建议。
A7: 同步文档 | B7: 对应 MD：docs/superpowers/specs/2026-05-20-single-stage-family-asset-diagnosis-design.md

Sheet 示例输入
A1: 示例输入
A2: 当前填入一个中等收入单身样本，可直接替换 B 列数值进行测试。
A4: 资产负债表 | B4: 金额 | C4: 单位 | D4: 说明
A5: 总资产 | B5: 1050000 | C5: 元 | D5: 全部资产合计
A6: 总负债 | B6: 280000 | C6: 元 | D6: 房贷、车贷、消费贷等合计
A7: 净资产 | B7: =B5-B6 -> 770000 | C7: 元 | D7: 总资产 - 总负债
A8: 流动资产 | B8: 70000 | C8: 元 | D8: 现金、活期、货币基金等
A9: 短期负债 | B9: 20000 | C9: 元 | D9: 一年内需偿还的短期债务
A10: 生息资产 | B10: 260000 | C10: 元 | D10: 可产生利息、分红、收益的资产
A11: 可投资资产 | B11: 330000 | C11: 元 | D11: 流动资产 + 可配置投资资产
A12: 长期投资资产 | B12: 230000 | C12: 元 | D12: 基金、股票、养老金账户等长期资产
A13: 年被动收入 | B13: 12000 | C13: 元 | D13: 理财、股息、租金等非工作收入
A14: 年投资收益 | B14: 12000 | C14: 元 | D14: 当年投资收益
A15: 期初投资资产 | B15: 230000 | C15: 元 | D15: 用于计算投资报酬率
A17: 收支储蓄表 | B17: 金额 | C17: 单位 | D17: 说明
A18: 年收入 | B18: 360000 | C18: 元 | D18: 税后总收入
A19: 年支出 | B19: 300000 | C19: 元 | D19: 全年总支出
A20: 月必要支出 | B20: 25000 | C20: 元 | D20: 必要生活成本、房租房贷、基本开销
A21: 固定支出 | B21: 210000 | C21: 元 | D21: 房租/房贷、通勤、基本生活等刚性支出
A22: 年债务本息支出 | B22: 110000 | C22: 元 | D22: 全年还款本金和利息
A23: 高息消费贷余额 | B23: 60000 | C23: 元 | D23: 信用卡滚债、消费贷等
A24: 年保费 | B24: 16000 | C24: 元 | D24: 商业保险年保费
A25: 已配置基础保障项 | B25: 2 | C25: 项 | D25: 医保、意外、重疾等
A26: 应配置基础保障项 | B26: 3 | C26: 项 | D26: 单身期 MVP 默认 3 项
A27: 有效重大风险保障额度 | B27: 900000 | C27: 元 | D27: 可覆盖重大疾病、意外、收入中断等风险的额度

Sheet 指标参数
A1: 指标参数
A2: 参数表是后续校准的核心：权重、m、k 和锚点都应可配置。
A4: 维度 | B4: 维度权重 | C4: 指标 | D4: 维度内权重 | E4: 公式 | F4: 方向 | G4: m | H4: k | I4: 评分类型 | J4: 经验锚点
A5: 偿债能力 | B5: 0.2 | C5: 资产负债率 | D5: 0.3 | E5: 总负债 / 总资产 | F5: 越低越好 | G5: 0.4 | H5: -10 | I5: s | J5: 20%优，40%中点，60%警示
A6: 偿债能力 | B6: 0.2 | C6: 债务偿付率 | D6: 0.45 | E6: 年债务本息 / 年收入 | F6: 越低越好 | G6: 0.25 | H6: -12 | I6: s | J6: 10%优，25%中点，40%警示
A7: 偿债能力 | B7: 0.2 | C7: 高息负债收入比 | D7: 0.25 | E7: 高息消费贷余额 / 年收入 | F7: 越低越好 | G7: 0.1 | H7: -25 | I7: s | J7: 0%优，10%警示，20%红灯
A8: 流动性 | B8: 0.2 | C8: 紧急备用金倍数 | D8: 0.5 | E8: 流动资产 / 月必要支出 | F8: 越高越好 | G8: 3 | H8: 1.1 | I8: s | J8: 1个月红灯，3个月中点，5-6个月优
A9: 流动性 | B9: 0.2 | C9: 净流动覆盖倍数 | D9: 0.25 | E9: (流动资产 - 短期负债) / 月必要支出 | F9: 越高越好 | G9: 2 | H9: 1.2 | I9: s | J9: 0红灯，2中点，4优
A10: 流动性 | B10: 0.2 | C10: 流动资产占比 | D10: 0.25 | E10: 流动资产 / 总资产 | F10: 越高越好 | G10: 0.15 | H10: 12 | I10: s | J10: 5%红灯，15%中点，30%优
A11: 储蓄能力 | B11: 0.22 | C11: 总结余率 | D11: 0.45 | E11: (收入 - 支出) / 收入 | F11: 越高越好 | G11: 0.2 | H11: 12 | I11: s | J11: 5%红灯，20%中点，35%优
A12: 储蓄能力 | B12: 0.22 | C12: 自由储蓄率 | D12: 0.35 | E12: (收入 - 固定支出 - 债务本息) / 收入 | F12: 越高越好 | G12: 0.15 | H12: 12 | I12: s | J12: 0%红灯，15%中点，30%优
A13: 储蓄能力 | B13: 0.22 | C13: 支出刚性比率 | D13: 0.2 | E13: 固定支出 / 总支出 | F13: 越低越好 | G13: 0.6 | H13: -8 | I13: s | J13: 40%优，60%中点，80%警示
A14: 成长能力 | B14: 0.15 | C14: 生息资产占比 | D14: 0.35 | E14: 生息资产 / 总资产 | F14: 越高越好 | G14: 0.35 | H14: 8 | I14: s | J14: 15%红灯，35%中点，55%优
A15: 成长能力 | B15: 0.15 | C15: 长期投资资产占比 | D15: 0.35 | E15: 长期投资资产 / 可投资资产 | F15: 越高越好 | G15: 0.5 | H15: 8 | I15: s | J15: 20%红灯，50%中点，70%优
A16: 成长能力 | B16: 0.15 | C16: 投资报酬率 | D16: 0.3 | E16: 年投资收益 / 期初投资资产 | F16: 越高越好 | G16: 0.04 | H16: 12 | I16: s | J16: 0%低，4%中点，8%优
... A21: 财富自由度 | B21: 0.08 | C21: 净资产支出倍数 | D21: 0.5 | E21: 净资产 / 年支出 | F21: 越高越好 | G21: 1 | H21: 1.1 | I21: s | J21: 0低，1倍中点，3倍优

Sheet 评分计算
A1: 评分计算
A2: 根据示例输入计算原始指标、S 曲线得分、状态和加权分。
A4: 维度 | B4: 指标 | C4: 原始值 | D4: 展示值 | E4: 指标得分 | F4: 状态 | G4: 维度内权重 | H4: 加权分 | I4: 公式口径
A5: 偿债能力 | B5: 资产负债率 | C5: ='示例输入'!B6/'示例输入'!B5 -> 0.26666667 | D5: 26.7% | E5: =100/(1+EXP(10*(C5-0.4))) -> 79.139147 | F5: =IF(E5>=70,"绿灯",IF(E5>=55,"黄灯","红灯")) -> 绿灯 | G5: 0.3 | H5: =E5*G5 -> 23.741744 | I5: 总负债 / 总资产
A6: 偿债能力 | B6: 债务偿付率 | C6: ='示例输入'!B22/'示例输入'!B18 -> 0.30555556 | D6: 30.6% | E6: =100/(1+EXP(12*(C6-0.25))) -> 33.924363 | F6: =IF(E6>=70,"绿灯",IF(E6>=55,"黄灯","红灯")) -> 红灯 | G6: 0.45 | H6: =E6*G6 -> 15.265963 | I6: 年债务本息 / 年收入
A7: 偿债能力 | B7: 高息负债收入比 | C7: ='示例输入'!B23/'示例输入'!B18 -> 0.16666667 | D7: 16.7% | E7: =100/(1+EXP(25*(C7-0.1))) -> 15.88691 | F7: =IF(E7>=70,"绿灯",IF(E7>=55,"黄灯","红灯")) -> 红灯 | G7: 0.25 | H7: =E7*G7 -> 3.9717276 | I7: 高息消费贷余额 / 年收入
A8: 流动性 | B8: 紧急备用金倍数 | C8: ='示例输入'!B8/'示例输入'!B20 -> 2.8 | D8: 2.8倍 | E8: =100/(1+EXP(-1.1*(C8-3))) -> 44.522076 | F8: =IF(E8>=70,"绿灯",IF(E8>=55,"黄灯","红灯")) -> 红灯 | G8: 0.5 | H8: =E8*G8 -> 22.261038 | I8: 流动资产 / 月必要支出
A9: 流动性 | B9: 净流动覆盖倍数 | C9: =('示例输入'!B8-'示例输入'!B9)/'示例输入'!B20 -> 2 | D9: 2.0倍 | E9: =100/(1+EXP(-1.2*(C9-2))) -> 50 | F9: =IF(E9>=70,"绿灯",IF(E9>=55,"黄灯","红灯")) -> 红灯 | G9: 0.25 | H9: =E9*G9 -> 12.5 | I9: (流动资产 - 短期负债) / 月必要支出
A10: 流动性 | B10: 流动资产占比 | C10: ='示例输入'!B8/'示例输入'!B5 -> 0.066666667 | D10: 6.7% | E10: =100/(1+EXP(-12*(C10-0.15))) -> 26.894142 | F10: =IF(E10>=70,"绿灯",IF(E10>=55,"黄灯","红灯")) -> 红灯 | G10: 0.25 | H10: =E10*G10 -> 6.7235355 | I10: 流动资产 / 总资产
A11: 储蓄能力 | B11: 总结余率 | C11: =('示例输入'!B18-'示例输入'!B19)/'示例输入'!B18 -> 0.16666667 | D11: 16.7% | E11: =100/(1+EXP(-12*(C11-0.2))) -> 40.131234 | F11: =IF(E11>=70,"绿灯",IF(E11>=55,"黄灯","红灯")) -> 红灯 | G11: 0.45 | H11: =E11*G11 -> 18.059055 | I11: (收入 - 支出) / 收入
A12: 储蓄能力 | B12: 自由储蓄率 | C12: =('示例输入'!B18-'示例输入'!B21-'示例输入'!B22)/'示例输入'!B18 -> 0.11111111 | D12: 11.1% | E12: =100/(1+EXP(-12*(C12-0.15))) -> 38.54055 | F12: =IF(E12>=70,"绿灯",IF(E12>=55,"黄灯","红灯")) -> 红灯 | G12: 0.35 | H12: =E12*G12 -> 13.489193 | I12: (收入 - 固定支出 - 债务本息) / 收入
A13: 储蓄能力 | B13: 支出刚性比率 | C13: ='示例输入'!B21/'示例输入'!B19 -> 0.7 | D13: 70.0% | E13: =100/(1+EXP(8*(C13-0.6))) -> 31.002552 | F13: =IF(E13>=70,"绿灯",IF(E13>=55,"黄灯","红灯")) -> 红灯 | G13: 0.2 | H13: =E13*G13 -> 6.2005104 | I13: 固定支出 / 总支出
A14: 成长能力 | B14: 生息资产占比 | C14: ='示例输入'!B10/'示例输入'!B5 -> 0.24761905 | D14: 24.8% | E14: =100/(1+EXP(-8*(C14-0.35))) -> 30.596586 | F14: =IF(E14>=70,"绿灯",IF(E14>=55,"黄灯","红灯")) -> 红灯 | G14: 0.35 | H14: =E14*G14 -> 10.708805 | I14: 生息资产 / 总资产
A15: 成长能力 | B15: 长期投资资产占比 | C15: ='示例输入'!B12/'示例输入'!B11 -> 0.6969697 | D15: 69.7% | E15: =100/(1+EXP(-8*(C15-0.5))) -> 82.860285 | F15: =IF(E15>=70,"绿灯",IF(E15>=55,"黄灯","红灯")) -> 绿灯 | G15: 0.35 | H15: =E15*G15 -> 29.0011 | I15: 长期投资资产 / 可投资资产
A16: 成长能力 | B16: 投资报酬率 | C16: ='示例输入'!B14/'示例输入'!B15 -> 0.052173913 | D16: 5.2% | E16: =100/(1+EXP(-12*(C16-0.04))) -> 53.645693 | F16: =IF(E16>=70,"绿灯",IF(E16>=55,"黄灯","红灯")) -> 红灯 | G16: 0.3 | H16: =E16*G16 -> 16.093708 | I16: 年投资收益 / 期初投资资产
A17: 保障能力 | B17: 基础保障完整度 | C17: ='示例输入'!B25/'示例输入'!B26 -> 0.66666667 | D17: 66.7% | E17: =100/(1+EXP(-8*(C17-0.6))) -> 63.026022 | F17: =IF(E17>=70,"绿灯",IF(E17>=55,"黄灯","红灯")) -> 黄灯 | G17: 0.35 | H17: =E17*G17 -> 22.059108 | I17: 已配置基础保障项 / 应配置基础保障项
A18: 保障能力 | B18: 保费收入比 | C18: ='示例输入'!B24/'示例输入'!B18 -> 0.044444444 | D18: 4.4% | E18: =IF(C18<0.05,100/(1+EXP(-50*(C18-0.05))),IF(C18<=0.12,95,IF(C18<=0.2,95-(C18-0.12)/0.08*35,MAX(20,60-(C18-0.2)/0.1*40)))) -> 43.099867 | F18: =IF(E18>=70,"绿灯",IF(E18>=55,"黄灯","红灯")) -> 红灯 | G18: 0.3 | H18: =E18*G18 -> 12.92996 | I18: 年保费 / 年收入
A19: 保障能力 | B19: 重大风险覆盖倍数 | C19: ='示例输入'!B27/('示例输入'!B20*12) -> 3 | D19: 3.0倍 | E19: =100/(1+EXP(-0.8*(C19-3))) -> 50 | F19: =IF(E19>=70,"绿灯",IF(E19>=55,"黄灯","红灯")) -> 红灯 | G19: 0.35 | H19: =E19*G19 -> 17.5 | I19: 有效保障额度 / 年必要支出
A20: 财富自由度 | B20: 被动收入覆盖率 | C20: ='示例输入'!B13/'示例输入'!B19 -> 0.04 | D20: 4.0% | E20: =100/(1+EXP(-8*(C20-0.1))) -> 38.225213 | F20: =IF(E20>=70,"绿灯",IF(E20>=55,"黄灯","红灯")) -> 红灯 | G20: 0.5 | H20: =E20*G20 -> 19.112606 | I20: 年被动收入 / 年支出
A21: 财富自由度 | B21: 净资产支出倍数 | C21: ='示例输入'!B7/'示例输入'!B19 -> 2.5666667 | D21: 2.6倍 | E21: =100/(1+EXP(-1.1*(C21-1))) -> 84.855769 | F21: =IF(E21>=70,"绿灯",IF(E21>=55,"黄灯","红灯")) -> 绿灯 | G21: 0.5 | H21: =E21*G21 -> 42.427885 | I21: 净资产 / 年支出

Sheet 六维总览
A1: 六维总览
A2: 综合分、六维分数、红黄绿状态和一句话诊断。
A4: =SUMPRODUCT(B8:B13,C8:C13) -> 46.4 | C4: =IF(A4>=70,"绿灯",IF(A4>=55,"黄灯","红灯")) -> 红灯 | D4: 整体处于基础待改善状态：偿债压力和储蓄能力会影响后续成长能力，流动性安全垫需要优先观察。
A7: 维度 | B7: 权重 | C7: 维度得分 | D7: 状态 | E7: 定位 | F7: 颜色
A8: 储蓄能力 | B8: 0.22 | C8: =SUMIFS('评分计算'!H:H,'评分计算'!A:A,A8) -> 37.748758 | D8: =IF(C8>=70,"绿灯",IF(C8>=55,"黄灯","红灯")) -> 红灯 | E8: 收入转化为资产的核心发动机
A9: 流动性 | B9: 0.2 | C9: =SUMIFS('评分计算'!H:H,'评分计算'!A:A,A9) -> 41.484574 | D9: =IF(C9>=70,"绿灯",IF(C9>=55,"黄灯","红灯")) -> 红灯 | E9: 防止突发事件击穿财务安全
A10: 偿债能力 | B10: 0.2 | C10: =SUMIFS('评分计算'!H:H,'评分计算'!A:A,A10) -> 42.979435 | D10: =IF(C10>=70,"绿灯",IF(C10>=55,"黄灯","红灯")) -> 红灯 | E10: 控制负债规模和还款压力
A11: 保障能力 | B11: 0.15 | C11: =SUMIFS('评分计算'!H:H,'评分计算'!A:A,A11) -> 52.489068 | D11: =IF(C11>=70,"绿灯",IF(C11>=55,"黄灯","红灯")) -> 红灯 | E11: 转移重大风险，避免一次事故归零
A12: 成长能力 | B12: 0.15 | C12: =SUMIFS('评分计算'!H:H,'评分计算'!A:A,A12) -> 55.803613 | D12: =IF(C12>=70,"绿灯",IF(C12>=55,"黄灯","红灯")) -> 黄灯 | E12: 判断资产是否具备长期增值能力
A13: 财富自由度 | B13: 0.08 | C13: =SUMIFS('评分计算'!H:H,'评分计算'!A:A,A13) -> 61.540491 | D13: =IF(C13>=70,"绿灯",IF(C13>=55,"黄灯","红灯")) -> 黄灯 | E13: 结果性指标，单身期低权重保留

Sheet 连锁诊断
A1: 连锁诊断
A2: 解释维度之间的传导关系：先找起点问题，再给前置修复动作。
A4: 强度 | B4: 传导链条 | C4: 触发条件 | D4: 当前证据 | E4: 影响解释 | F4: 优先行动 | G4: 是否触发
A5: 强 | B5: 储蓄能力 -> 成长能力 | C5: 储蓄能力低于60分，或自由储蓄率低于10% | D5: 储蓄能力 37.7 分，自由储蓄率 11.1% | E5: 新增可投资资金不足，长期资产配置改善速度受限。 | F5: 先提高月度结余和自由储蓄率，再逐步增加长期投资资产。 | G5: =IF(OR('六维总览'!C8<60,'评分计算'!C12<0.1),"是","否") -> 是
A6: 中 | B6: 储蓄能力 -> 流动性 | C6: 总结余率低于10%，且紧急备用金低于3个月 | D6: 总结余率 16.7%，备用金 2.8倍 | E6: 很难靠未来现金流快速补足安全垫。 | F6: 压缩非必要支出，把新增结余优先补入流动账户。 | G6: =IF(AND('评分计算'!C11<0.1,'评分计算'!C8<3),"是","否") -> 否
A7: 强 | B7: 偿债能力 -> 流动性 | C7: 债务偿付率高于30%，或高息负债收入比高于10% | D7: 债务偿付率 30.6%，高息负债收入比 16.7% | E7: 还款占用现金流，收入波动时更容易出现短期资金缺口。 | F7: 优先处理高息负债，并避免继续扩大固定还款义务。 | G7: =IF(OR('评分计算'!C6>0.3,'评分计算'!C7>0.1),"是","否") -> 是
A8: 中 | B8: 偿债能力 -> 成长能力 | C8: 债务偿付率高于30%，且长期投资资产占比低于50% | D8: 债务偿付率 30.6%，长期投资资产占比 69.7% | E8: 债务支出挤压长期投资，资产增长速度受限。 | F8: 降低还款压力后，再提高长期投资资产占比。 | G8: =IF(AND('评分计算'!C6>0.3,'评分计算'!C15<0.5),"是","否") -> 否
A9: 强 | B9: 保障能力 -> 流动性 | C9: 基础保障完整度低于60%，且紧急备用金低于3个月 | D9: 保障完整度 66.7%，备用金 2.8倍 | E9: 医疗、意外或收入中断事件可能快速消耗备用金。 | F9: 先补齐基础保障，再同步建立紧急备用金。 | G9: =IF(AND('评分计算'!C17<0.6,'评分计算'!C8<3),"是","否") -> 否
A10: 中 | B10: 流动性 -> 成长能力 | C10: 紧急备用金低于3个月，且长期投资资产占比较高 | D10: 备用金 2.8倍，长期投资资产占比 69.7% | E10: 安全垫不足时继续投资，突发支出时可能被迫卖出资产。 | F10: 暂停增加高波动资产，先把备用金补到3个月以上。 | G10: =IF(AND('评分计算'!C8<3,'评分计算'!C15>0.5),"是","否") -> 是
A11: 弱 | B11: 成长能力 -> 财富自由度 | C11: 成长能力低于60分，且被动收入覆盖率低于10% | D11: 成长能力 55.8 分，被动收入覆盖率 4.0% | E11: 资产缺乏增值和现金流贡献，财富自由进度偏慢。 | F11: 在安全底座稳定后，逐步提高生息资产和长期投资资产占比。 | G11: =IF(AND('六维总览'!C12<60,'评分计算'!C20<0.1),"是","否") -> 是

Sheet 建议库
A1: 建议库
A2: MVP 只输出方向性改善动作，不输出产品级推荐。
A4: 优先级 | B4: 类别 | C4: 触发条件 | D4: 建议话术 | E4: 资产结构方向
A5: 1 | B5: 急性风险 | C5: 月结余 < 0 | D5: 先让现金流转正，暂停非必要大额支出和高波动投资。 | E5: 提高现金类资产，减少消费性支出。
A6: 1 | B6: 流动性 | C6: 紧急备用金 < 3个月 | D6: 优先补足至少3个月必要支出的紧急备用金。 | E6: 新增结余优先进入现金/货币类账户。
A7: 1 | B7: 偿债 | C7: 高息负债收入比 > 10% | D7: 优先偿还高息消费贷，避免利息侵蚀储蓄能力。 | E7: 降低负债，释放现金流。
A8: 2 | B8: 保障 | C8: 基础保障完整度 < 60% | D8: 补齐医保、意外、重疾等基础保障，避免风险事件击穿资产。 | E8: 用合理保费换取重大风险转移。
A9: 3 | B9: 储蓄 | C9: 总结余率 < 20% | D9: 优化支出结构，提高收入转化为资产的效率。 | E9: 提高每月可投资现金流。
A10: 4 | B10: 成长 | C10: 生息资产占比 < 35% | D10: 在流动性安全后，逐步提高生息资产和长期资产占比。 | E10: 从闲置资金转向长期增值资产。
A11: 5 | B11: 自由度 | C11: 被动收入覆盖率 < 10% | D11: 财富自由度是结果指标，先修复储蓄、负债、流动性和成长能力。 | E11: 长期提高资产现金流贡献。
